sentinel_analysis/__init__.py
sentinel_analysis/alert.py
sentinel_analysis/main.py
sentinel_analysis/report.py
sentinel_analysis-0.1.5.dist-info/LICENSE
sentinel_analysis-0.1.5.dist-info/METADATA
sentinel_analysis-0.1.5.dist-info/WHEEL
sentinel_analysis-0.1.5.dist-info/entry_points.txt
sentinel_analysis-0.1.5.dist-info/RECORD
